[
    {
        "token": "Обзор",
        "freq": 3
    },
    {
        "token": "смартфона",
        "freq": 3
    },
    {
        "token": "Highscreen",
        "freq": 12
    },
    {
        "token": "Prime",
        "freq": 16
    },
    {
        "token": "L",
        "freq": 15
    },
    {
        "token": "Содержание",
        "freq": 1
    },
    {
        "token": "Характеристики",
        "freq": 2
    },
    {
        "token": "Комплект",
        "freq": 2
    },
    {
        "token": "поставки",
        "freq": 2
    },
    {
        "token": "Введение",
        "freq": 2
    },
    {
        "token": "Дизайн",
        "freq": 2
    },
    {
        "token": "размеры",
        "freq": 2
    },
    {
        "token": "управляющие",
        "freq": 2
    },
    {
        "token": "элементы",
        "freq": 2
    },
    {
        "token": "Дисплей",
        "freq": 2
    },
    {
        "token": "Аккумулятор",
        "freq": 2
    },
    {
        "token": "Коммуникационные",
        "freq": 2
    },
    {
        "token": "возможности",
        "freq": 2
    },
    {
        "token": "Память",
        "freq": 3
    },
    {
        "token": "и",
        "freq": 51
    },
    {
        "token": "карта",
        "freq": 2
    },
    {
        "token": "памяти",
        "freq": 6
    },
    {
        "token": "Камера",
        "freq": 3
    },
    {
        "token": "Производительность",
        "freq": 2
    },
    {
        "token": "программная",
        "freq": 2
    },
    {
        "token": "платформа",
        "freq": 2
    },
    {
        "token": "Мультимедиа",
        "freq": 2
    },
    {
        "token": "Заключение",
        "freq": 2
    },
    {
        "token": "Класс",
        "freq": 1
    },
    {
        "token": ":",
        "freq": 35
    },
    {
        "token": "смартфон",
        "freq": 1
    },
    {
        "token": "Материалы",
        "freq": 1
    },
    {
        "token": "корпуса",
        "freq": 2
    },
    {
        "token": "пластик",
        "freq": 1
    },
    {
        "token": "Операционная",
        "freq": 2
    },
    {
        "token": "система",
        "freq": 2
    },
    {
        "token": "Google",
        "freq": 2
    },
    {
        "token": "Android",
        "freq": 3
    },
    {
        "token": "5.1",
        "freq": 2
    },
    {
        "token": "Lollipop",
        "freq": 1
    },
    {
        "token": "Сеть",
        "freq": 1
    },
    {
        "token": "2G/3G/4G",
        "freq": 1
    },
    {
        "token": "Процессор",
        "freq": 1
    },
    {
        "token": "4",
        "freq": 2
    },
    {
        "token": "ядра",
        "freq": 2
    },
    {
        "token": "1300",
        "freq": 1
    },
    {
        "token": "МГц",
        "freq": 3
    },
    {
        "token": "MediaTek",
        "freq": 2
    },
    {
        "token": "MT6735",
        "freq": 2
    },
    {
        "token": "Оперативная",
        "freq": 1
    },
    {
        "token": "память",
        "freq": 2
    },
    {
        "token": "2",
        "freq": 7
    },
    {
        "token": "ГБ",
        "freq": 7
    },
    {
        "token": "для",
        "freq": 8
    },
    {
        "token": "хранения",
        "freq": 1
    },
    {
        "token": "данных",
        "freq": 1
    },
    {
        "token": "16",
        "freq": 5
    },
    {
        "token": "Интерфейсы",
        "freq": 1
    },
    {
        "token": "Wi-Fi",
        "freq": 2
    },
    {
        "token": "(",
        "freq": 27
    },
    {
        "token": "b/g/n",
        "freq": 2
    },
    {
        "token": ")",
        "freq": 27
    },
    {
        "token": "Bluetooth",
        "freq": 2
    },
    {
        "token": "4.0",
        "freq": 2
    },
    {
        "token": "разъем",
        "freq": 1
    },
    {
        "token": "microUSB",
        "freq": 3
    },
    {
        "token": "USB",
        "freq": 2
    },
    {
        "token": "2.0",
        "freq": 1
    },
    {
        "token": "заряда/синхронизации",
        "freq": 1
    },
    {
        "token": "3.5",
        "freq": 2
    },
    {
        "token": "мм",
        "freq": 8
    },
    {
        "token": "гарнитуры",
        "freq": 1
    },
    {
        "token": "Экран",
        "freq": 1
    },
    {
        "token": "емкостный",
        "freq": 1
    },
    {
        "token": "IPS",
        "freq": 2
    },
    {
        "token": "5",
        "freq": 6
    },
    {
        "token": "''",
        "freq": 1
    },
    {
        "token": "с",
        "freq": 16
    },
    {
        "token": "разрешением",
        "freq": 1
    },
    {
        "token": "720x1280",
        "freq": 1
    },
    {
        "token": "точек",
        "freq": 2
    },
    {
        "token": "8",
        "freq": 3
    },
    {
        "token": "МП",
        "freq": 5
    },
    {
        "token": "c",
        "freq": 1
    },
    {
        "token": "автофокусом",
        "freq": 2
    },
    {
        "token": "+",
        "freq": 1
    },
    {
        "token": "вспышка",
        "freq": 1
    },
    {
        "token": "Навигация",
        "freq": 1
    },
    {
        "token": "GPS/ГЛОНАСС",
        "freq": 1
    },
    {
        "token": "Дополнительно",
        "freq": 1
    },
    {
        "token": "сенсоры",
        "freq": 1
    },
    {
        "token": "приближения",
        "freq": 2
    },
    {
        "token": "освещения",
        "freq": 3
    },
    {
        "token": "Батарея",
        "freq": 1
    },
    {
        "token": "съемная",
        "freq": 1
    },
    {
        "token": "литий-полимерная",
        "freq": 1
    },
    {
        "token": "Li-Pol",
        "freq": 2
    },
    {
        "token": "емкостью",
        "freq": 2
    },
    {
        "token": "2300",
        "freq": 2
    },
    {
        "token": "мАч",
        "freq": 2
    },
    {
        "token": "Габариты",
        "freq": 2
    },
    {
        "token": "143.5x72x8.3",
        "freq": 2
    },
    {
        "token": "Вес",
        "freq": 1
    },
    {
        "token": "145",
        "freq": 2
    },
    {
        "token": "г",
        "freq": 2
    },
    {
        "token": "Смартфон",
        "freq": 6
    },
    {
        "token": "Сетевой",
        "freq": 1
    },
    {
        "token": "адаптер",
        "freq": 1
    },
    {
        "token": "USB-кабель",
        "freq": 1
    },
    {
        "token": "Три",
        "freq": 1
    },
    {
        "token": "панельки",
        "freq": 1
    },
    {
        "token": "черная",
        "freq": 2
    },
    {
        "token": "оранжевая",
        "freq": 2
    },
    {
        "token": "голубая",
        "freq": 2
    },
    {
        "token": "Гарантийный",
        "freq": 1
    },
    {
        "token": "талон",
        "freq": 1
    },
    {
        "token": "Инструкция",
        "freq": 1
    },
    {
        "token": "был",
        "freq": 1
    },
    {
        "token": "представлен",
        "freq": 1
    },
    {
        "token": "в",
        "freq": 20
    },
    {
        "token": "апреле",
        "freq": 1
    },
    {
        "token": "этого",
        "freq": 1
    },
    {
        "token": "года",
        "freq": 1
    },
    {
        "token": "Он",
        "freq": 1
    },
    {
        "token": "продолжает",
        "freq": 1
    },
    {
        "token": "линейку",
        "freq": 1
    },
    {
        "token": "устройств",
        "freq": 3
    },
    {
        "token": "серии",
        "freq": 1
    },
    {
        "token": "это",
        "freq": 4
    },
    {
        "token": "аппараты",
        "freq": 1
    },
    {
        "token": "комплект",
        "freq": 1
    },
    {
        "token": "к",
        "freq": 5
    },
    {
        "token": "которым",
        "freq": 1
    },
    {
        "token": "дополнительно",
        "freq": 1
    },
    {
        "token": "были",
        "freq": 1
    },
    {
        "token": "включены",
        "freq": 1
    },
    {
        "token": "несколько",
        "freq": 3
    },
    {
        "token": "панелек",
        "freq": 1
    },
    {
        "token": "на",
        "freq": 18
    },
    {
        "token": "заднюю",
        "freq": 1
    },
    {
        "token": "сторону",
        "freq": 2
    },
    {
        "token": "Обычно",
        "freq": 1
    },
    {
        "token": "недорогие",
        "freq": 1
    },
    {
        "token": "смартфоны",
        "freq": 3
    },
    {
        "token": "ярким",
        "freq": 1
    },
    {
        "token": "внешним",
        "freq": 1
    },
    {
        "token": "видом",
        "freq": 1
    },
    {
        "token": "неплохими",
        "freq": 1
    },
    {
        "token": "техническими",
        "freq": 1
    },
    {
        "token": "характеристиками",
        "freq": 1
    },
    {
        "token": "Новинка",
        "freq": 1
    },
    {
        "token": "от",
        "freq": 9
    },
    {
        "token": "предлагает",
        "freq": 1
    },
    {
        "token": "три",
        "freq": 1
    },
    {
        "token": "крышки",
        "freq": 3
    },
    {
        "token": "классического",
        "freq": 1
    },
    {
        "token": "черного",
        "freq": 2
    },
    {
        "token": "цвета",
        "freq": 6
    },
    {
        "token": "голубого",
        "freq": 1
    },
    {
        "token": "оранжевого",
        "freq": 1
    },
    {
        "token": "С",
        "freq": 3
    },
    {
        "token": "точки",
        "freq": 1
    },
    {
        "token": "зрения",
        "freq": 1
    },
    {
        "token": "параметров",
        "freq": 1
    },
    {
        "token": "здесь",
        "freq": 2
    },
    {
        "token": "все",
        "freq": 5
    },
    {
        "token": "более-менее",
        "freq": 1
    },
    {
        "token": "неплохо",
        "freq": 2
    },
    {
        "token": "четырехъядерный",
        "freq": 1
    },
    {
        "token": "чип",
        "freq": 1
    },
    {
        "token": "поддержкой",
        "freq": 2
    },
    {
        "token": "LTE",
        "freq": 2
    },
    {
        "token": "ОЗУ",
        "freq": 2
    },
    {
        "token": "есть",
        "freq": 5
    },
    {
        "token": "GPS",
        "freq": 2
    },
    {
        "token": "ГЛОНАСС",
        "freq": 2
    },
    {
        "token": "две",
        "freq": 1
    },
    {
        "token": "симкарты",
        "freq": 2
    },
    {
        "token": "качественная",
        "freq": 1
    },
    {
        "token": "камера",
        "freq": 6
    },
    {
        "token": "Стоит",
        "freq": 2
    },
    {
        "token": "гаджет",
        "freq": 1
    },
    {
        "token": "чуть",
        "freq": 2
    },
    {
        "token": "менее",
        "freq": 1
    },
    {
        "token": "10",
        "freq": 5
    },
    {
        "token": "000",
        "freq": 8
    },
    {
        "token": "рублей",
        "freq": 8
    },
    {
        "token": "имеет",
        "freq": 4
    },
    {
        "token": "классический",
        "freq": 1
    },
    {
        "token": "эргономичный",
        "freq": 1
    },
    {
        "token": "дизайн",
        "freq": 1
    },
    {
        "token": "прямоугольной",
        "freq": 1
    },
    {
        "token": "формой",
        "freq": 1
    },
    {
        "token": "покатыми",
        "freq": 1
    },
    {
        "token": "углами",
        "freq": 1
    },
    {
        "token": "типичны",
        "freq": 1
    },
    {
        "token": "аппарата",
        "freq": 1
    },
    {
        "token": "5-дюймовой",
        "freq": 1
    },
    {
        "token": "диагональю",
        "freq": 1
    },
    {
        "token": "однако",
        "freq": 6
    },
    {
        "token": "весит",
        "freq": 1
    },
    {
        "token": "больше",
        "freq": 1
    },
    {
        "token": "учитывая",
        "freq": 1
    },
    {
        "token": "что",
        "freq": 5
    },
    {
        "token": "он",
        "freq": 1
    },
    {
        "token": "выполнен",
        "freq": 1
    },
    {
        "token": "полностью",
        "freq": 1
    },
    {
        "token": "из",
        "freq": 5
    },
    {
        "token": "пластика",
        "freq": 3
    },
    {
        "token": "чем",
        "freq": 1
    },
    {
        "token": "ближайшие",
        "freq": 1
    },
    {
        "token": "конкуренты",
        "freq": 1
    },
    {
        "token": "граммов",
        "freq": 1
    },
    {
        "token": "Лицевая",
        "freq": 2
    },
    {
        "token": "панель",
        "freq": 1
    },
    {
        "token": "темная",
        "freq": 1
    },
    {
        "token": "тонкие",
        "freq": 1
    },
    {
        "token": "рамки",
        "freq": 1
    },
    {
        "token": "сделаны",
        "freq": 1
    },
    {
        "token": "глянцевого",
        "freq": 1
    },
    {
        "token": "Помимо",
        "freq": 1
    },
    {
        "token": "задние",
        "freq": 1
    },
    {
        "token": "немного",
        "freq": 4
    },
    {
        "token": "отличаются",
        "freq": 1
    },
    {
        "token": "друг",
        "freq": 1
    },
    {
        "token": "друга",
        "freq": 1
    },
    {
        "token": "материалами",
        "freq": 1
    },
    {
        "token": "покрыта",
        "freq": 1
    },
    {
        "token": "слоем",
        "freq": 1
    },
    {
        "token": "софт-тач",
        "freq": 1
    },
    {
        "token": "полуглянцевого",
        "freq": 1
    },
    {
        "token": "Они",
        "freq": 1
    },
    {
        "token": "нескользкие",
        "freq": 1
    },
    {
        "token": "руке",
        "freq": 1
    },
    {
        "token": "аппарат",
        "freq": 4
    },
    {
        "token": "лежит",
        "freq": 1
    },
    {
        "token": "отлично",
        "freq": 1
    },
    {
        "token": "Фронтальная",
        "freq": 1
    },
    {
        "token": "сторона",
        "freq": 2
    },
    {
        "token": "защищена",
        "freq": 1
    },
    {
        "token": "стеклом",
        "freq": 2
    },
    {
        "token": "Asahi",
        "freq": 1
    },
    {
        "token": "Glass",
        "freq": 1
    },
    {
        "token": "Dragontrail",
        "freq": 1
    },
    {
        "token": "практически",
        "freq": 4
    },
    {
        "token": "оснащены",
        "freq": 1
    },
    {
        "token": "этим",
        "freq": 1
    },
    {
        "token": "За",
        "freq": 1
    },
    {
        "token": "недель",
        "freq": 1
    },
    {
        "token": "использования",
        "freq": 2
    },
    {
        "token": "поверхности",
        "freq": 2
    },
    {
        "token": "дисплея",
        "freq": 2
    },
    {
        "token": "не",
        "freq": 10
    },
    {
        "token": "осталось",
        "freq": 1
    },
    {
        "token": "крупных",
        "freq": 1
    },
    {
        "token": "царапин",
        "freq": 1
    },
    {
        "token": "или",
        "freq": 3
    },
    {
        "token": "сколов",
        "freq": 1
    },
    {
        "token": "Олеофобное",
        "freq": 1
    },
    {
        "token": "покрытие",
        "freq": 2
    },
    {
        "token": "присутствует",
        "freq": 2
    },
    {
        "token": "оно",
        "freq": 1
    },
    {
        "token": "среднее",
        "freq": 1
    },
    {
        "token": "качество",
        "freq": 2
    },
    {
        "token": "отпечатки",
        "freq": 1
    },
    {
        "token": "сильно",
        "freq": 1
    },
    {
        "token": "заметны",
        "freq": 2
    },
    {
        "token": "удаляются",
        "freq": 1
    },
    {
        "token": "относительно",
        "freq": 2
    },
    {
        "token": "быстро",
        "freq": 2
    },
    {
        "token": "палец",
        "freq": 1
    },
    {
        "token": "по",
        "freq": 7
    },
    {
        "token": "скользит",
        "freq": 1
    },
    {
        "token": "хорошо",
        "freq": 2
    },
    {
        "token": "На",
        "freq": 1
    },
    {
        "token": "крышках",
        "freq": 1
    },
    {
        "token": "тоже",
        "freq": 1
    },
    {
        "token": "остаются",
        "freq": 1
    },
    {
        "token": "следы",
        "freq": 1
    },
    {
        "token": "но",
        "freq": 5
    },
    {
        "token": "они",
        "freq": 3
    },
    {
        "token": "незаметны",
        "freq": 1
    },
    {
        "token": "Сверху",
        "freq": 1
    },
    {
        "token": "фронтальной",
        "freq": 2
    },
    {
        "token": "части",
        "freq": 1
    },
    {
        "token": "гаджета",
        "freq": 1
    },
    {
        "token": "расположены",
        "freq": 2
    },
    {
        "token": "датчики",
        "freq": 1
    },
    {
        "token": "функционируют",
        "freq": 1
    },
    {
        "token": "без",
        "freq": 5
    },
    {
        "token": "нареканий",
        "freq": 1
    },
    {
        "token": "динамик",
        "freq": 2
    },
    {
        "token": "Спикер",
        "freq": 1
    },
    {
        "token": "высокую",
        "freq": 1
    },
    {
        "token": "громкость",
        "freq": 1
    },
    {
        "token": "запаса",
        "freq": 1
    },
    {
        "token": "нет",
        "freq": 3
    },
    {
        "token": "собеседника",
        "freq": 1
    },
    {
        "token": "слышно",
        "freq": 1
    },
    {
        "token": "четко",
        "freq": 1
    },
    {
        "token": "разборчиво",
        "freq": 1
    },
    {
        "token": "тембр",
        "freq": 1
    },
    {
        "token": "приятный",
        "freq": 1
    },
    {
        "token": "бубнящий",
        "freq": 1
    },
    {
        "token": "Индикатор",
        "freq": 1
    },
    {
        "token": "событий",
        "freq": 1
    },
    {
        "token": "увы",
        "freq": 1
    },
    {
        "token": "отсутствует",
        "freq": 1
    },
    {
        "token": "Под",
        "freq": 2
    },
    {
        "token": "дисплеем",
        "freq": 1
    },
    {
        "token": "расположились",
        "freq": 1
    },
    {
        "token": "стандартные",
        "freq": 1
    },
    {
        "token": "кнопки",
        "freq": 2
    },
    {
        "token": "ОС",
        "freq": 1
    },
    {
        "token": "Меню",
        "freq": 1
    },
    {
        "token": "Домой",
        "freq": 1
    },
    {
        "token": "Назад",
        "freq": 1
    },
    {
        "token": "Обозначены",
        "freq": 1
    },
    {
        "token": "тонкими",
        "freq": 1
    },
    {
        "token": "символами",
        "freq": 1
    },
    {
        "token": "серебристой",
        "freq": 1
    },
    {
        "token": "краской",
        "freq": 1
    },
    {
        "token": "Подсветки",
        "freq": 1
    },
    {
        "token": "Снизу",
        "freq": 1
    },
    {
        "token": "микрофон",
        "freq": 1
    },
    {
        "token": "сверху",
        "freq": 2
    },
    {
        "token": "аудиовыход",
        "freq": 1
    },
    {
        "token": "наушники",
        "freq": 1
    },
    {
        "token": "справа",
        "freq": 2
    },
    {
        "token": "находятся",
        "freq": 1
    },
    {
        "token": "пластиковые",
        "freq": 1
    },
    {
        "token": "питания",
        "freq": 1
    },
    {
        "token": "регулирования",
        "freq": 1
    },
    {
        "token": "громкости",
        "freq": 2
    },
    {
        "token": "крышкой",
        "freq": 1
    },
    {
        "token": "два",
        "freq": 2
    },
    {
        "token": "слота",
        "freq": 1
    },
    {
        "token": "под",
        "freq": 2
    },
    {
        "token": "формата",
        "freq": 1
    },
    {
        "token": "micro",
        "freq": 1
    },
    {
        "token": "слот",
        "freq": 1
    },
    {
        "token": "карты",
        "freq": 2
    },
    {
        "token": "microSD",
        "freq": 2
    },
    {
        "token": "Boost",
        "freq": 1
    },
    {
        "token": "3",
        "freq": 3
    },
    {
        "token": "Power",
        "freq": 7
    },
    {
        "token": "Rage",
        "freq": 2
    },
    {
        "token": "Ice",
        "freq": 3
    },
    {
        "token": "Four",
        "freq": 1
    },
    {
        "token": "К",
        "freq": 13
    },
    {
        "token": "содержанию",
        "freq": 9
    },
    {
        "token": "В",
        "freq": 7
    },
    {
        "token": "этом",
        "freq": 1
    },
    {
        "token": "устройстве",
        "freq": 1
    },
    {
        "token": "используется",
        "freq": 4
    },
    {
        "token": "экран",
        "freq": 1
    },
    {
        "token": "диагональ",
        "freq": 1
    },
    {
        "token": "которого",
        "freq": 1
    },
    {
        "token": "составляет",
        "freq": 2
    },
    {
        "token": "дюймов",
        "freq": 1
    },
    {
        "token": "Физический",
        "freq": 1
    },
    {
        "token": "размер",
        "freq": 1
    },
    {
        "token": "62х111",
        "freq": 1
    },
    {
        "token": "рамка",
        "freq": 1
    },
    {
        "token": "снизу",
        "freq": 1
    },
    {
        "token": "18",
        "freq": 1
    },
    {
        "token": "слева",
        "freq": 1
    },
    {
        "token": "примерно",
        "freq": 2
    },
    {
        "token": "Присутствует",
        "freq": 1
    },
    {
        "token": "антибликовое",
        "freq": 1
    },
    {
        "token": "Разрешение",
        "freq": 1
    },
    {
        "token": "HD",
        "freq": 2
    },
    {
        "token": "то",
        "freq": 3
    },
    {
        "token": "720х1280",
        "freq": 1
    },
    {
        "token": "плотность",
        "freq": 1
    },
    {
        "token": "293",
        "freq": 1
    },
    {
        "token": "пикселя",
        "freq": 1
    },
    {
        "token": "дюйм",
        "freq": 1
    },
    {
        "token": "Матрица",
        "freq": 1
    },
    {
        "token": "OGS",
        "freq": 1
    },
    {
        "token": "Максимальная",
        "freq": 1
    },
    {
        "token": "яркость",
        "freq": 3
    },
    {
        "token": "белого",
        "freq": 2
    },
    {
        "token": "442",
        "freq": 1
    },
    {
        "token": "кд/м2",
        "freq": 2
    },
    {
        "token": "максимальная",
        "freq": 1
    },
    {
        "token": "0,40",
        "freq": 1
    },
    {
        "token": "Контрастность",
        "freq": 1
    },
    {
        "token": "1100:1",
        "freq": 1
    },
    {
        "token": "Углы",
        "freq": 2
    },
    {
        "token": "обзора",
        "freq": 3
    },
    {
        "token": "максимальные",
        "freq": 1
    },
    {
        "token": "определенным",
        "freq": 1
    },
    {
        "token": "наклоном",
        "freq": 1
    },
    {
        "token": "картинка",
        "freq": 2
    },
    {
        "token": "может",
        "freq": 2
    },
    {
        "token": "даже",
        "freq": 2
    },
    {
        "token": "слегка",
        "freq": 1
    },
    {
        "token": "инвертироваться",
        "freq": 1
    },
    {
        "token": "заметно",
        "freq": 1
    },
    {
        "token": "кадрах",
        "freq": 1
    },
    {
        "token": "темным",
        "freq": 1
    },
    {
        "token": "фоном",
        "freq": 1
    },
    {
        "token": "Данные",
        "freq": 1
    },
    {
        "token": "калибратора",
        "freq": 2
    },
    {
        "token": "График",
        "freq": 2
    },
    {
        "token": "яркости",
        "freq": 4
    },
    {
        "token": "норма",
        "freq": 1
    },
    {
        "token": "Гамма",
        "freq": 1
    },
    {
        "token": "идеальное",
        "freq": 1
    },
    {
        "token": "значение",
        "freq": 1
    },
    {
        "token": "RGB-уровней",
        "freq": 2
    },
    {
        "token": "синий",
        "freq": 1
    },
    {
        "token": "избытке",
        "freq": 1
    },
    {
        "token": "а",
        "freq": 4
    },
    {
        "token": "красный",
        "freq": 1
    },
    {
        "token": "зеленый",
        "freq": 1
    },
    {
        "token": "идеально",
        "freq": 1
    },
    {
        "token": "Температура",
        "freq": 1
    },
    {
        "token": "среднем",
        "freq": 1
    },
    {
        "token": "около",
        "freq": 11
    },
    {
        "token": "7800",
        "freq": 1
    },
    {
        "token": "максимальной",
        "freq": 1
    },
    {
        "token": "увеличивается",
        "freq": 1
    },
    {
        "token": "до",
        "freq": 5
    },
    {
        "token": "8600",
        "freq": 2
    },
    {
        "token": "К.",
        "freq": 1
    },
    {
        "token": "Треугольник",
        "freq": 1
    },
    {
        "token": "sRGB",
        "freq": 1
    },
    {
        "token": "левая",
        "freq": 1
    },
    {
        "token": "смещена",
        "freq": 1
    },
    {
        "token": "центру",
        "freq": 1
    },
    {
        "token": "целом",
        "freq": 2
    },
    {
        "token": "Судя",
        "freq": 1
    },
    {
        "token": "данным",
        "freq": 1
    },
    {
        "token": "матрица",
        "freq": 2
    },
    {
        "token": "очень",
        "freq": 5
    },
    {
        "token": "хорошие",
        "freq": 1
    },
    {
        "token": "показатели",
        "freq": 1
    },
    {
        "token": "высокая",
        "freq": 2
    },
    {
        "token": "контрастность",
        "freq": 1
    },
    {
        "token": "идеальные",
        "freq": 1
    },
    {
        "token": "значения",
        "freq": 3
    },
    {
        "token": "гаммы",
        "freq": 1
    },
    {
        "token": "натуральная",
        "freq": 1
    },
    {
        "token": "цветопередача",
        "freq": 1
    },
    {
        "token": "Минусы",
        "freq": 2
    },
    {
        "token": "серый",
        "freq": 2
    },
    {
        "token": "цвет",
        "freq": 2
    },
    {
        "token": "примесью",
        "freq": 1
    },
    {
        "token": "других",
        "freq": 1
    },
    {
        "token": "оттенков",
        "freq": 1
    },
    {
        "token": "температура",
        "freq": 1
    },
    {
        "token": "зависимости",
        "freq": 1
    },
    {
        "token": "подсветки",
        "freq": 1
    },
    {
        "token": "изменяется",
        "freq": 1
    },
    {
        "token": "7600",
        "freq": 1
    },
    {
        "token": "глаз",
        "freq": 1
    },
    {
        "token": "эта",
        "freq": 1
    },
    {
        "token": "разница",
        "freq": 1
    },
    {
        "token": "незаметна",
        "freq": 1
    },
    {
        "token": "Настройки",
        "freq": 1
    },
    {
        "token": "Засветка",
        "freq": 1
    },
    {
        "token": "Белый",
        "freq": 1
    },
    {
        "token": "Поведение",
        "freq": 1
    },
    {
        "token": "свету",
        "freq": 1
    },
    {
        "token": "тени",
        "freq": 1
    },
    {
        "token": "данной",
        "freq": 1
    },
    {
        "token": "модели",
        "freq": 1
    },
    {
        "token": "съемный",
        "freq": 1
    },
    {
        "token": "литий-полимерный",
        "freq": 1
    },
    {
        "token": "аккумулятор",
        "freq": 1
    },
    {
        "token": "функционирует",
        "freq": 3
    },
    {
        "token": "7-8",
        "freq": 1
    },
    {
        "token": "часов",
        "freq": 2
    },
    {
        "token": "активном",
        "freq": 1
    },
    {
        "token": "режиме",
        "freq": 1
    },
    {
        "token": "подключением",
        "freq": 1
    },
    {
        "token": "3G/4G",
        "freq": 1
    },
    {
        "token": "получаса",
        "freq": 1
    },
    {
        "token": "разговоров",
        "freq": 1
    },
    {
        "token": "часа",
        "freq": 4
    },
    {
        "token": "камеры",
        "freq": 4
    },
    {
        "token": "столько",
        "freq": 1
    },
    {
        "token": "же",
        "freq": 3
    },
    {
        "token": "просмотра",
        "freq": 1
    },
    {
        "token": "видео",
        "freq": 6
    },
    {
        "token": "3-4",
        "freq": 1
    },
    {
        "token": "Twitter",
        "freq": 3
    },
    {
        "token": "почте",
        "freq": 1
    },
    {
        "token": "Если",
        "freq": 1
    },
    {
        "token": "захотите",
        "freq": 1
    },
    {
        "token": "поиграть",
        "freq": 1
    },
    {
        "token": "рассчитывайте",
        "freq": 1
    },
    {
        "token": "час-полтора",
        "freq": 1
    },
    {
        "token": "при",
        "freq": 3
    },
    {
        "token": "полной",
        "freq": 2
    },
    {
        "token": "звука",
        "freq": 1
    },
    {
        "token": "выводом",
        "freq": 1
    },
    {
        "token": "Проигрывание",
        "freq": 1
    },
    {
        "token": "6",
        "freq": 1
    },
    {
        "token": "От",
        "freq": 1
    },
    {
        "token": "штатного",
        "freq": 1
    },
    {
        "token": "сетевого",
        "freq": 1
    },
    {
        "token": "адаптера",
        "freq": 1
    },
    {
        "token": "батарейка",
        "freq": 2
    },
    {
        "token": "заряжается",
        "freq": 1
    },
    {
        "token": "за",
        "freq": 4
    },
    {
        "token": "2.5",
        "freq": 2
    },
    {
        "token": "ПК",
        "freq": 1
    },
    {
        "token": "5-5.5",
        "freq": 1
    },
    {
        "token": "поддерживает",
        "freq": 1
    },
    {
        "token": "работу",
        "freq": 1
    },
    {
        "token": "двумя",
        "freq": 1
    },
    {
        "token": "симкартами",
        "freq": 1
    },
    {
        "token": "Каждая",
        "freq": 1
    },
    {
        "token": "них",
        "freq": 1
    },
    {
        "token": "2G/3G",
        "freq": 1
    },
    {
        "token": "4G",
        "freq": 1
    },
    {
        "token": "Сети",
        "freq": 1
    },
    {
        "token": "GSM/GPRS/EDGE",
        "freq": 1
    },
    {
        "token": "850/900/1800/1900",
        "freq": 1
    },
    {
        "token": "3G/HSPA+",
        "freq": 1
    },
    {
        "token": "900/2100",
        "freq": 1
    },
    {
        "token": "4G/LTE",
        "freq": 1
    },
    {
        "token": "3/7/8/20",
        "freq": 1
    },
    {
        "token": "Естественно",
        "freq": 1
    },
    {
        "token": "стандарта",
        "freq": 1
    },
    {
        "token": "версии",
        "freq": 2
    },
    {
        "token": "последним",
        "freq": 1
    },
    {
        "token": "двум",
        "freq": 1
    },
    {
        "token": "у",
        "freq": 2
    },
    {
        "token": "меня",
        "freq": 1
    },
    {
        "token": "возникли",
        "freq": 1
    },
    {
        "token": "вопросы",
        "freq": 1
    },
    {
        "token": "спутники",
        "freq": 1
    },
    {
        "token": "определяются",
        "freq": 1
    },
    {
        "token": "долго",
        "freq": 1
    },
    {
        "token": "порой",
        "freq": 1
    },
    {
        "token": "приходится",
        "freq": 2
    },
    {
        "token": "ждать",
        "freq": 1
    },
    {
        "token": "минут",
        "freq": 1
    },
    {
        "token": "потом",
        "freq": 1
    },
    {
        "token": "сигнал",
        "freq": 1
    },
    {
        "token": "держится",
        "freq": 1
    },
    {
        "token": "стабильно",
        "freq": 1
    },
    {
        "token": "точность",
        "freq": 2
    },
    {
        "token": "пары",
        "freq": 1
    },
    {
        "token": "метров",
        "freq": 2
    },
    {
        "token": "помещении",
        "freq": 1
    },
    {
        "token": "например",
        "freq": 1
    },
    {
        "token": "рядом",
        "freq": 1
    },
    {
        "token": "окном",
        "freq": 1
    },
    {
        "token": "резко",
        "freq": 1
    },
    {
        "token": "ухудшается",
        "freq": 1
    },
    {
        "token": "погрешность",
        "freq": 1
    },
    {
        "token": "уже",
        "freq": 2
    },
    {
        "token": "100",
        "freq": 1
    },
    {
        "token": "Режим",
        "freq": 2
    },
    {
        "token": "OTG",
        "freq": 1
    },
    {
        "token": "подключение",
        "freq": 1
    },
    {
        "token": "внешних",
        "freq": 1
    },
    {
        "token": "поддерживается",
        "freq": 1
    },
    {
        "token": "Внутри",
        "freq": 1
    },
    {
        "token": "стоит",
        "freq": 1
    },
    {
        "token": "оперативной",
        "freq": 1
    },
    {
        "token": "Для",
        "freq": 2
    },
    {
        "token": "подобного",
        "freq": 1
    },
    {
        "token": "устройства",
        "freq": 2
    },
    {
        "token": "такое",
        "freq": 1
    },
    {
        "token": "количество",
        "freq": 1
    },
    {
        "token": "хороший",
        "freq": 1
    },
    {
        "token": "результат",
        "freq": 1
    },
    {
        "token": "Встроенной",
        "freq": 1
    },
    {
        "token": "Доступно",
        "freq": 1
    },
    {
        "token": "11",
        "freq": 1
    },
    {
        "token": "Конечно",
        "freq": 1
    },
    {
        "token": "поддерживаются",
        "freq": 1
    },
    {
        "token": "максимальный",
        "freq": 1
    },
    {
        "token": "объем",
        "freq": 1
    },
    {
        "token": "32",
        "freq": 1
    },
    {
        "token": "их",
        "freq": 1
    },
    {
        "token": "определения",
        "freq": 1
    },
    {
        "token": "системе",
        "freq": 1
    },
    {
        "token": "перезагружать",
        "freq": 1
    },
    {
        "token": "Очень",
        "freq": 1
    },
    {
        "token": "странное",
        "freq": 1
    },
    {
        "token": "явление",
        "freq": 1
    },
    {
        "token": "Здесь",
        "freq": 1
    },
    {
        "token": "модуля",
        "freq": 1
    },
    {
        "token": "собственно",
        "freq": 1
    },
    {
        "token": "как",
        "freq": 3
    },
    {
        "token": "любом",
        "freq": 1
    },
    {
        "token": "другом",
        "freq": 1
    },
    {
        "token": "аналогичном",
        "freq": 1
    },
    {
        "token": "смартфоне",
        "freq": 1
    },
    {
        "token": "основной",
        "freq": 1
    },
    {
        "token": "диафрагма",
        "freq": 2
    },
    {
        "token": "F2.2",
        "freq": 2
    },
    {
        "token": "фронтальный",
        "freq": 1
    },
    {
        "token": "широкий",
        "freq": 1
    },
    {
        "token": "угол",
        "freq": 1
    },
    {
        "token": "Насколько",
        "freq": 1
    },
    {
        "token": "я",
        "freq": 1
    },
    {
        "token": "понял",
        "freq": 1
    },
    {
        "token": "точно",
        "freq": 1
    },
    {
        "token": "такой",
        "freq": 2
    },
    {
        "token": "близкий",
        "freq": 1
    },
    {
        "token": "качеству",
        "freq": 1
    },
    {
        "token": "картинки",
        "freq": 1
    },
    {
        "token": "модуль",
        "freq": 1
    },
    {
        "token": "предыдущих",
        "freq": 1
    },
    {
        "token": "смартфонах",
        "freq": 1
    },
    {
        "token": "Five",
        "freq": 1
    },
    {
        "token": "так",
        "freq": 4
    },
    {
        "token": "далее",
        "freq": 3
    },
    {
        "token": "Днем",
        "freq": 1
    },
    {
        "token": "достаточно",
        "freq": 1
    },
    {
        "token": "приятная",
        "freq": 1
    },
    {
        "token": "яркие",
        "freq": 1
    },
    {
        "token": "хорошая",
        "freq": 2
    },
    {
        "token": "резкость",
        "freq": 1
    },
    {
        "token": "Однако",
        "freq": 1
    },
    {
        "token": "присутствуют",
        "freq": 1
    },
    {
        "token": "характерные",
        "freq": 1
    },
    {
        "token": "бюджетных",
        "freq": 1
    },
    {
        "token": "модулей",
        "freq": 1
    },
    {
        "token": "Sony",
        "freq": 1
    },
    {
        "token": "артефакты",
        "freq": 1
    },
    {
        "token": "особенно",
        "freq": 2
    },
    {
        "token": "углам",
        "freq": 1
    },
    {
        "token": "фотографий",
        "freq": 2
    },
    {
        "token": "Динамический",
        "freq": 1
    },
    {
        "token": "диапазон",
        "freq": 1
    },
    {
        "token": "нулевой",
        "freq": 1
    },
    {
        "token": "если",
        "freq": 1
    },
    {
        "token": "попробовать",
        "freq": 1
    },
    {
        "token": "поиграться",
        "freq": 1
    },
    {
        "token": "экспозицией",
        "freq": 1
    },
    {
        "token": "готовой",
        "freq": 1
    },
    {
        "token": "фотографии",
        "freq": 2
    },
    {
        "token": "вытянуть",
        "freq": 1
    },
    {
        "token": "кадр",
        "freq": 1
    },
    {
        "token": "получится",
        "freq": 1
    },
    {
        "token": "Ночные",
        "freq": 1
    },
    {
        "token": "мутные",
        "freq": 1
    },
    {
        "token": "нерезкие",
        "freq": 1
    },
    {
        "token": "Положение",
        "freq": 1
    },
    {
        "token": "спасти",
        "freq": 1
    },
    {
        "token": "ручная",
        "freq": 1
    },
    {
        "token": "настройка",
        "freq": 1
    },
    {
        "token": "выдержки",
        "freq": 2
    },
    {
        "token": "ISO",
        "freq": 2
    },
    {
        "token": "Основная",
        "freq": 1
    },
    {
        "token": "пишет",
        "freq": 1
    },
    {
        "token": "разрешении",
        "freq": 1
    },
    {
        "token": "FullHD",
        "freq": 1
    },
    {
        "token": "25",
        "freq": 1
    },
    {
        "token": "к/с",
        "freq": 4
    },
    {
        "token": "хорошее",
        "freq": 1
    },
    {
        "token": "освещение",
        "freq": 1
    },
    {
        "token": "недостаточные",
        "freq": 1
    },
    {
        "token": "условия",
        "freq": 1
    },
    {
        "token": "Картинка",
        "freq": 1
    },
    {
        "token": "широкоугольная",
        "freq": 1
    },
    {
        "token": "четкость",
        "freq": 1
    },
    {
        "token": "шумов",
        "freq": 1
    },
    {
        "token": "мало",
        "freq": 1
    },
    {
        "token": "фокус",
        "freq": 1
    },
    {
        "token": "медленный",
        "freq": 1
    },
    {
        "token": "неточный",
        "freq": 1
    },
    {
        "token": "Звук",
        "freq": 1
    },
    {
        "token": "среднего",
        "freq": 1
    },
    {
        "token": "качества",
        "freq": 1
    },
    {
        "token": "30",
        "freq": 1
    },
    {
        "token": "днем",
        "freq": 1
    },
    {
        "token": "ночью",
        "freq": 1
    },
    {
        "token": "ручные",
        "freq": 2
    },
    {
        "token": "настройки",
        "freq": 2
    },
    {
        "token": "фокуса",
        "freq": 1
    },
    {
        "token": "баланса",
        "freq": 1
    },
    {
        "token": "называется",
        "freq": 1
    },
    {
        "token": "Pro",
        "freq": 6
    },
    {
        "token": "Примеры",
        "freq": 1
    },
    {
        "token": "режим",
        "freq": 4
    },
    {
        "token": "фронтальная",
        "freq": 2
    },
    {
        "token": "Пример",
        "freq": 3
    },
    {
        "token": "1",
        "freq": 2
    },
    {
        "token": "MP4",
        "freq": 3
    },
    {
        "token": "52",
        "freq": 1
    },
    {
        "token": "МБ",
        "freq": 3
    },
    {
        "token": "17",
        "freq": 1
    },
    {
        "token": "работает",
        "freq": 1
    },
    {
        "token": "тайваньском",
        "freq": 1
    },
    {
        "token": "чипсете",
        "freq": 1
    },
    {
        "token": "Это",
        "freq": 1
    },
    {
        "token": "64-битный",
        "freq": 1
    },
    {
        "token": "SoC",
        "freq": 1
    },
    {
        "token": "который",
        "freq": 1
    },
    {
        "token": "содержит",
        "freq": 1
    },
    {
        "token": "ARM",
        "freq": 1
    },
    {
        "token": "Cortex-53",
        "freq": 1
    },
    {
        "token": "техпроцесс",
        "freq": 1
    },
    {
        "token": "28",
        "freq": 1
    },
    {
        "token": "нм",
        "freq": 1
    },
    {
        "token": "тактовая",
        "freq": 1
    },
    {
        "token": "частота",
        "freq": 1
    },
    {
        "token": "каждого",
        "freq": 1
    },
    {
        "token": "1.5",
        "freq": 1
    },
    {
        "token": "ГГц",
        "freq": 1
    },
    {
        "token": "качестве",
        "freq": 1
    },
    {
        "token": "графики",
        "freq": 1
    },
    {
        "token": "Mali",
        "freq": 1
    },
    {
        "token": "T-720",
        "freq": 1
    },
    {
        "token": "Open",
        "freq": 2
    },
    {
        "token": "GL",
        "freq": 1
    },
    {
        "token": "ES",
        "freq": 1
    },
    {
        "token": "3.0",
        "freq": 1
    },
    {
        "token": "CL",
        "freq": 1
    },
    {
        "token": "1.2",
        "freq": 1
    },
    {
        "token": "API",
        "freq": 1
    },
    {
        "token": "Интерфейс",
        "freq": 1
    },
    {
        "token": "каких-либо",
        "freq": 1
    },
    {
        "token": "лагов",
        "freq": 1
    },
    {
        "token": "тормозов",
        "freq": 1
    },
    {
        "token": "играми",
        "freq": 1
    },
    {
        "token": "типичная",
        "freq": 1
    },
    {
        "token": "ситуация",
        "freq": 1
    },
    {
        "token": "запускаются",
        "freq": 1
    },
    {
        "token": "некоторые",
        "freq": 1
    },
    {
        "token": "сложные",
        "freq": 1
    },
    {
        "token": "игры",
        "freq": 1
    },
    {
        "token": "могут",
        "freq": 1
    },
    {
        "token": "подтормаживать",
        "freq": 1
    },
    {
        "token": "простыми",
        "freq": 1
    },
    {
        "token": "проблем",
        "freq": 1
    },
    {
        "token": "Тесты",
        "freq": 1
    },
    {
        "token": "производительности",
        "freq": 1
    },
    {
        "token": "фирменной",
        "freq": 1
    },
    {
        "token": "оболочки",
        "freq": 1
    },
    {
        "token": "Каких-либо",
        "freq": 1
    },
    {
        "token": "апдейтов",
        "freq": 1
    },
    {
        "token": "скорее",
        "freq": 1
    },
    {
        "token": "всего",
        "freq": 1
    },
    {
        "token": "будет",
        "freq": 1
    },
    {
        "token": "Музыкальный",
        "freq": 1
    },
    {
        "token": "плеер",
        "freq": 1
    },
    {
        "token": "фирменный",
        "freq": 1
    },
    {
        "token": "При",
        "freq": 1
    },
    {
        "token": "запуске",
        "freq": 1
    },
    {
        "token": "автоматически",
        "freq": 1
    },
    {
        "token": "сканирует",
        "freq": 1
    },
    {
        "token": "наличие",
        "freq": 1
    },
    {
        "token": "мелодий",
        "freq": 1
    },
    {
        "token": "Работает",
        "freq": 1
    },
    {
        "token": "папками",
        "freq": 1
    },
    {
        "token": "Громкость",
        "freq": 2
    },
    {
        "token": "наушниках",
        "freq": 1
    },
    {
        "token": "Качество",
        "freq": 1
    },
    {
        "token": "классное",
        "freq": 1
    },
    {
        "token": "подобных",
        "freq": 1
    },
    {
        "token": "надо",
        "freq": 1
    },
    {
        "token": "слушать",
        "freq": 1
    },
    {
        "token": "Мне",
        "freq": 1
    },
    {
        "token": "понравилось",
        "freq": 1
    },
    {
        "token": "Есть",
        "freq": 3
    },
    {
        "token": "эквалайзер",
        "freq": 1
    },
    {
        "token": "готовые",
        "freq": 1
    },
    {
        "token": "пресеты",
        "freq": 1
    },
    {
        "token": "динамика",
        "freq": 1
    },
    {
        "token": "средняя",
        "freq": 1
    },
    {
        "token": "выше",
        "freq": 1
    },
    {
        "token": "средней",
        "freq": 1
    },
    {
        "token": "неплохое",
        "freq": 1
    },
    {
        "token": "Радио",
        "freq": 1
    },
    {
        "token": "получился",
        "freq": 1
    },
    {
        "token": "вполне",
        "freq": 1
    },
    {
        "token": "неплохой",
        "freq": 1
    },
    {
        "token": "Думаю",
        "freq": 1
    },
    {
        "token": "приглянется",
        "freq": 1
    },
    {
        "token": "молодому",
        "freq": 1
    },
    {
        "token": "поколению",
        "freq": 1
    },
    {
        "token": "лето",
        "freq": 1
    },
    {
        "token": "комплекте",
        "freq": 1
    },
    {
        "token": "можно",
        "freq": 1
    },
    {
        "token": "найти",
        "freq": 2
    },
    {
        "token": "цветные",
        "freq": 1
    },
    {
        "token": "тыльную",
        "freq": 1
    },
    {
        "token": "У",
        "freq": 1
    },
    {
        "token": "Вобис",
        "freq": 1
    },
    {
        "token": "Компьютер",
        "freq": 1
    },
    {
        "token": "иной",
        "freq": 1
    },
    {
        "token": "раз",
        "freq": 2
    },
    {
        "token": "выходят",
        "freq": 1
    },
    {
        "token": "такие",
        "freq": 1
    },
    {
        "token": "выделить-то",
        "freq": 1
    },
    {
        "token": "нечего",
        "freq": 1
    },
    {
        "token": "критиковать",
        "freq": 1
    },
    {
        "token": "Вот",
        "freq": 1
    },
    {
        "token": "девайс",
        "freq": 1
    },
    {
        "token": "экрана",
        "freq": 1
    },
    {
        "token": "слабые",
        "freq": 1
    },
    {
        "token": "углы",
        "freq": 1
    },
    {
        "token": "выдает",
        "freq": 1
    },
    {
        "token": "чистые",
        "freq": 1
    },
    {
        "token": "слабая",
        "freq": 1
    },
    {
        "token": "прожорливый",
        "freq": 1
    },
    {
        "token": "чипсет",
        "freq": 1
    },
    {
        "token": "самые",
        "freq": 1
    },
    {
        "token": "лучшие",
        "freq": 1
    },
    {
        "token": "И",
        "freq": 1
    },
    {
        "token": "Конкуренты",
        "freq": 1
    },
    {
        "token": "Xiaomi",
        "freq": 2
    },
    {
        "token": "Redmi",
        "freq": 2
    },
    {
        "token": "Всеми",
        "freq": 1
    },
    {
        "token": "любимый",
        "freq": 1
    },
    {
        "token": "производитель",
        "freq": 1
    },
    {
        "token": "The",
        "freq": 1
    },
    {
        "token": "best",
        "freq": 2
    },
    {
        "token": "of",
        "freq": 1
    },
    {
        "token": "the",
        "freq": 1
    },
    {
        "token": "Ни",
        "freq": 1
    },
    {
        "token": "один",
        "freq": 1
    },
    {
        "token": "обзор",
        "freq": 1
    },
    {
        "token": "обходится",
        "freq": 1
    },
    {
        "token": "участия",
        "freq": 1
    },
    {
        "token": "Сяоми",
        "freq": 1
    },
    {
        "token": "конкурентах",
        "freq": 1
    },
    {
        "token": "Не",
        "freq": 1
    },
    {
        "token": "напишешь",
        "freq": 1
    },
    {
        "token": "его",
        "freq": 1
    },
    {
        "token": "тексте",
        "freq": 1
    },
    {
        "token": "сочтут",
        "freq": 1
    },
    {
        "token": "продажным",
        "freq": 1
    },
    {
        "token": "писакой",
        "freq": 1
    },
    {
        "token": "естественно",
        "freq": 1
    },
    {
        "token": "гарантия",
        "freq": 1
    },
    {
        "token": "только",
        "freq": 2
    },
    {
        "token": "магазина",
        "freq": 1
    },
    {
        "token": "кого",
        "freq": 1
    },
    {
        "token": "волнует",
        "freq": 1
    },
    {
        "token": "России",
        "freq": 1
    },
    {
        "token": "Лучше",
        "freq": 1
    },
    {
        "token": "всем",
        "freq": 1
    },
    {
        "token": "параметрам",
        "freq": 1
    },
    {
        "token": "ASUS",
        "freq": 1
    },
    {
        "token": "Zenfone",
        "freq": 2
    },
    {
        "token": "Laser",
        "freq": 1
    },
    {
        "token": "Цена",
        "freq": 2
    },
    {
        "token": "12",
        "freq": 3
    },
    {
        "token": "ZTE",
        "freq": 1
    },
    {
        "token": "Blade",
        "freq": 1
    },
    {
        "token": "X7",
        "freq": 1
    },
    {
        "token": "По",
        "freq": 1
    },
    {
        "token": "сути",
        "freq": 1
    },
    {
        "token": "аналог",
        "freq": 1
    },
    {
        "token": "крышечек",
        "freq": 1
    },
    {
        "token": "Meizu",
        "freq": 2
    },
    {
        "token": "M2",
        "freq": 2
    },
    {
        "token": "mini",
        "freq": 2
    },
    {
        "token": "Можно",
        "freq": 1
    },
    {
        "token": "9",
        "freq": 1
    },
    {
        "token": "РСТ",
        "freq": 1
    },
    {
        "token": "Обзор-сравнение",
        "freq": 1
    },
    {
        "token": "Asus",
        "freq": 1
    },
    {
        "token": "Lazer",
        "freq": 1
    },
    {
        "token": "ZE601KL",
        "freq": 1
    },
    {
        "token": "Selfie",
        "freq": 1
    },
    {
        "token": "ZD551KL",
        "freq": 1
    },
    {
        "token": "еще",
        "freq": 1
    },
    {
        "token": "множество",
        "freq": 1
    },
    {
        "token": "разных",
        "freq": 1
    },
    {
        "token": "китайских",
        "freq": 1
    },
    {
        "token": "девайсов",
        "freq": 1
    },
    {
        "token": "цене",
        "freq": 1
    },
    {
        "token": "OUKITEL",
        "freq": 1
    },
    {
        "token": "K4000",
        "freq": 1
    },
    {
        "token": "Elephone",
        "freq": 1
    },
    {
        "token": "S2",
        "freq": 1
    },
    {
        "token": "Zopo",
        "freq": 1
    },
    {
        "token": "Hero",
        "freq": 1
    },
    {
        "token": "Smartisan",
        "freq": 1
    },
    {
        "token": "U1",
        "freq": 1
    },
    {
        "token": "тому",
        "freq": 1
    },
    {
        "token": "подобные",
        "freq": 1
    },
    {
        "token": "Все",
        "freq": 1
    },
    {
        "token": "новости",
        "freq": 1
    },
    {
        "token": "мира",
        "freq": 1
    },
    {
        "token": "android",
        "freq": 2
    },
    {
        "token": "также",
        "freq": 1
    },
    {
        "token": "интересные",
        "freq": 1
    },
    {
        "token": "статьи",
        "freq": 1
    },
    {
        "token": "авторские",
        "freq": 1
    },
    {
        "token": "колонки",
        "freq": 1
    },
    {
        "token": "конкурсы",
        "freq": 1
    },
    {
        "token": "android.mobile-review.com",
        "freq": 1
    },
    {
        "token": "об",
        "freq": 1
    },
    {
        "token": "Роман",
        "freq": 1
    },
    {
        "token": "Белых",
        "freq": 1
    },
    {
        "token": "romeowhite",
        "freq": 1
    },
    {
        "token": "yandex.ru",
        "freq": 1
    },
    {
        "token": "Instagram",
        "freq": 2
    },
    {
        "token": "Опубликовано",
        "freq": 1
    },
    {
        "token": "",
        "freq": 1
    },
    {
        "token": "мая",
        "freq": 1
    },
    {
        "token": "2016",
        "freq": 1
    },
    {
        "token": ".mobile_xlarge",
        "freq": 1
    },
    {
        "token": "{",
        "freq": 1
    },
    {
        "token": "transform",
        "freq": 1
    },
    {
        "token": "scale",
        "freq": 1
    },
    {
        "token": "margin-left",
        "freq": 1
    },
    {
        "token": "80px",
        "freq": 1
    },
    {
        "token": "}",
        "freq": 1
    },
    {
        "token": "Поделиться",
        "freq": 1
    },
    {
        "token": "Мы",
        "freq": 1
    },
    {
        "token": "социальных",
        "freq": 1
    },
    {
        "token": "сетях",
        "freq": 1
    },
    {
        "token": "ВКонтакте",
        "freq": 1
    },
    {
        "token": "Facebook",
        "freq": 1
    },
    {
        "token": "Telegram",
        "freq": 1
    },
    {
        "token": "Пожалуйста",
        "freq": 1
    },
    {
        "token": "включите",
        "freq": 1
    },
    {
        "token": "JavaScript",
        "freq": 1
    },
    {
        "token": "отображения",
        "freq": 1
    },
    {
        "token": "комментариев",
        "freq": 1
    },
    {
        "token": "статье",
        "freq": 1
    },
    {
        "token": "добавить",
        "freq": 1
    },
    {
        "token": "Пишите",
        "freq": 1
    },
    {
        "token": "...",
        "freq": 1
    },
    {
        "token": "eldar",
        "freq": 1
    },
    {
        "token": "mobile-review.com",
        "freq": 1
    }
]